powershap_rs/__init__.py
powershap_rs/powershap.py
powershap_rs/shap_wrappers/__init__.py
powershap_rs/shap_wrappers/shap_explainer.py
powershap_rs/shap_wrappers/shap_explainer_factory.py
powershap_rs/utils.py
powershap_rs-0.2.0.dist-info/LICENSE
powershap_rs-0.2.0.dist-info/METADATA
powershap_rs-0.2.0.dist-info/WHEEL
powershap_rs-0.2.0.dist-info/RECORD
