Metadata-Version: 2.1
Name: powershap_rs
Version: 0.2.0
Summary: Feature selection using statistical significance of shap values with powershap-statistical-analysis-rs
Home-page: https://github.com/carlos-quantexai/powershap-rs
License: MIT
Keywords: feature selection,shap,data-science,machine learning
Author: Jarne Verhaeghe, Jeroen Van Der Donckt
Requires-Python: >=3.9,<=3.12
Classifier: License :: OSI Approved :: MIT License
Classifier: Programming Language :: Python :: 3
Classifier: Programming Language :: Python :: 3.9
Classifier: Programming Language :: Python :: 3.10
Classifier: Programming Language :: Python :: 3.11
Classifier: Programming Language :: Python :: 3.12
Requires-Dist: catboost (>=1.0.5,<2.0.0)
Requires-Dist: pandas (>=1.3)
Requires-Dist: polars
Requires-Dist: powershap-statistical-analysis-rs
Requires-Dist: scikit-learn
Requires-Dist: shap (>=0.45.0,<0.46.0)
Requires-Dist: statsmodels (>=0.13.2,<0.14.0)
Project-URL: Repository, https://github.com/carlos-quantexai/powershap-rs
